{
  "schema_version": "1.1",
  "site": {
    "name": "Piecorner Woods, Bedmond",
    "lat": 51.72146,
    "lon": -0.407832
  },
  "survey": {
    "generated": "14 July 2026, 17:56",
    "survey_start": "11 Jul 2026 18:48",
    "survey_end": "12 Jul 2026 10:16",
    "has_timestamps": true,
    "n_species": 11,
    "n_files": 32
  },
  "heatmap": {
    "species": [
      "Magpie",
      "Great Spotted Woodpecker",
      "Carrion Crow",
      "Common Wood Pigeon",
      "European Robin",
      "Eurasian Treecreeper",
      "Coal Tit",
      "European Green Woodpecker",
      "Blue Tit",
      "Dunnock",
      "Jay"
    ],
    "hours": [
      "00:00",
      "01:00",
      "02:00",
      "03:00",
      "04:00",
      "05:00",
      "06:00",
      "07:00",
      "08:00",
      "09:00",
      "10:00",
      "11:00",
      "12:00",
      "13:00",
      "14:00",
      "15:00",
      "16:00",
      "17:00",
      "18:00",
      "19:00",
      "20:00",
      "21:00",
      "22:00",
      "23:00"
    ],
    "data": [
      [
        0,
        0,
        0,
        0,
        0,
        0,
        0,
        0,
        0,
        1,
        0,
        0,
        0,
        0,
        0,
        0,
        0,
        0,
        0,
        0,
        1,
        0,
        0,
        0
      ],
      [
        0,
        0,
        0,
        0,
        0,
        1,
        0,
        0,
        0,
        0,
        0,
        0,
        0,
        0,
        0,
        0,
        0,
        0,
        0,
        1,
        0,
        0,
        0,
        0
      ],
      [
        0,
        0,
        0,
        0,
        0,
        0,
        2,
        0,
        0,
        0,
        0,
        0,
        0,
        0,
        0,
        0,
        0,
        0,
        0,
        0,
        0,
        2,
        0,
        0
      ],
      [
        0,
        0,
        0,
        0,
        0,
        0,
        0,
        0,
        0,
        0,
        0,
        0,
        0,
        0,
        0,
        0,
        0,
        0,
        0,
        0,
        0,
        5,
        0,
        0
      ],
      [
        0,
        0,
        0,
        0,
        11,
        0,
        0,
        0,
        0,
        0,
        0,
        0,
        0,
        0,
        0,
        0,
        0,
        0,
        0,
        0,
        0,
        0,
        0,
        0
      ],
      [
        0,
        0,
        0,
        0,
        0,
        0,
        4,
        0,
        3,
        2,
        0,
        0,
        0,
        0,
        0,
        0,
        0,
        0,
        0,
        0,
        0,
        0,
        0,
        0
      ],
      [
        0,
        0,
        0,
        0,
        0,
        0,
        0,
        0,
        0,
        6,
        0,
        0,
        0,
        0,
        0,
        0,
        0,
        0,
        0,
        0,
        0,
        0,
        0,
        0
      ],
      [
        0,
        0,
        0,
        0,
        0,
        0,
        1,
        0,
        0,
        0,
        0,
        0,
        0,
        0,
        0,
        0,
        0,
        0,
        0,
        0,
        0,
        0,
        0,
        0
      ],
      [
        0,
        0,
        0,
        0,
        0,
        0,
        0,
        0,
        0,
        2,
        0,
        0,
        0,
        0,
        0,
        0,
        0,
        0,
        0,
        0,
        0,
        0,
        0,
        0
      ],
      [
        0,
        0,
        0,
        0,
        0,
        2,
        0,
        0,
        0,
        0,
        0,
        0,
        0,
        0,
        0,
        0,
        0,
        0,
        0,
        0,
        0,
        0,
        0,
        0
      ],
      [
        0,
        0,
        0,
        0,
        0,
        0,
        0,
        0,
        0,
        0,
        0,
        0,
        0,
        0,
        0,
        0,
        0,
        0,
        0,
        0,
        0,
        1,
        0,
        0
      ]
    ]
  },
  "accumulation_curve": {
    "labels": [
      "18:48",
      "19:25",
      "20:02",
      "20:39",
      "21:16",
      "21:53",
      "22:31",
      "23:08",
      "23:45",
      "00:22",
      "00:59",
      "01:36",
      "02:13",
      "02:50",
      "03:27",
      "04:04",
      "04:42",
      "05:19",
      "05:56",
      "06:33",
      "07:10",
      "07:47",
      "08:24",
      "09:01",
      "09:38",
      "10:16",
      "10:16"
    ],
    "counts": [
      0,
      1,
      1,
      1,
      5,
      5,
      5,
      5,
      5,
      5,
      5,
      5,
      5,
      5,
      5,
      5,
      6,
      7,
      7,
      9,
      9,
      9,
      9,
      9,
      11,
      11,
      11
    ]
  },
  "ambient_stats": {
    "User": {
      "clips": 11,
      "files": 1
    },
    "Wind": {
      "clips": 18,
      "files": 7
    },
    "Plane": {
      "clips": 26,
      "files": 8
    },
    "Movement": {
      "clips": 13,
      "files": 6
    }
  },
  "detected_redlist": [],
  "acoustic_health": {
    "biophony_minutes": 1.4,
    "anthropophony_minutes": 1.2,
    "geophony_minutes": 0.6,
    "total_active_minutes": 2.6,
    "acoustic_integrity_pct": 53.2,
    "ndsi_equivalent": 0.06,
    "health_category": "Compromised",
    "health_class": "compromised",
    "bng_condition": "Functional Failure",
    "dawn_chorus_integrity_pct": 100.0
  },
  "disturbance_index": {
    "has_people_or_dogs": false,
    "people_clips": 0,
    "dog_clips": 0,
    "disturbance_pct_of_survey": 0.0,
    "vulnerable_species_present": [
      "Dunnock"
    ],
    "high_risk_overlaps": [],
    "breeding_season_risk": true,
    "wca_indicator_13_status": "Pass",
    "wca_threshold": 5.0,
    "flushing_risk_score": 0,
    "risk_category": "None",
    "risk_class": "no-risk"
  },
  "ecological_verdict": "Site exhibits compromised acoustic integrity requiring immediate mitigation with negligible recreational disturbance.",
  "species": [
    {
      "common_name": "Magpie",
      "latin_name": "Pica pica",
      "best_confidence": 0.9991297125816345,
      "mean_confidence": 0.9538482427597046,
      "star_rating": 5,
      "is_marginal": false,
      "verification_reasons": [],
      "bng_categories": [],
      "bocc_status": "Green",
      "file_count": 2,
      "n_clips": 2,
      "first_detected": "2026-07-11T20:48:41.572698",
      "last_detected": "2026-07-12T09:52:48.933424",
      "peak_hour": 9,
      "hourly_counts": [
        0,
        0,
        0,
        0,
        0,
        0,
        0,
        0,
        0,
        1,
        0,
        0,
        0,
        0,
        0,
        0,
        0,
        0,
        0,
        0,
        1,
        0,
        0,
        0
      ],
      "clips": [
        {
          "id": "Magpie_1",
          "spectrogram": "bird_report_20260714_175629_media/spectrograms/Magpie_1.png",
          "audio_report_file": "bird_report_20260714_175629.html",
          "audio_anchor_id": "audio-Magpie_1",
          "source_file": "20260711_204800.WAV",
          "offset_s": 41.572698412698415,
          "timestamp": "11 Jul 2026 20:48:41",
          "confidence": 0.9991297125816345,
          "verified": true
        },
        {
          "id": "Magpie_2",
          "spectrogram": "bird_report_20260714_175629_media/spectrograms/Magpie_2.png",
          "audio_report_file": "bird_report_20260714_175629.html",
          "audio_anchor_id": "audio-Magpie_2",
          "source_file": "20260712_095200.WAV",
          "offset_s": 48.93342403628118,
          "timestamp": "12 Jul 2026 09:52:48",
          "confidence": 0.9085667729377747,
          "verified": true
        }
      ]
    },
    {
      "common_name": "Great Spotted Woodpecker",
      "latin_name": "Dendrocopos major",
      "best_confidence": 0.9989627599716187,
      "mean_confidence": 0.8468078374862671,
      "star_rating": 5,
      "is_marginal": false,
      "verification_reasons": [],
      "bng_categories": [
        "canopy",
        "deadwood"
      ],
      "bocc_status": "Green",
      "file_count": 2,
      "n_clips": 2,
      "first_detected": "2026-07-11T19:20:55.829751",
      "last_detected": "2026-07-12T05:44:04.629751",
      "peak_hour": 5,
      "hourly_counts": [
        0,
        0,
        0,
        0,
        0,
        1,
        0,
        0,
        0,
        0,
        0,
        0,
        0,
        0,
        0,
        0,
        0,
        0,
        0,
        1,
        0,
        0,
        0,
        0
      ],
      "clips": [
        {
          "id": "Great_Spotted_Woodpecker_1",
          "spectrogram": "bird_report_20260714_175629_media/spectrograms/Great_Spotted_Woodpecker_1.png",
          "audio_report_file": "bird_report_20260714_175629.html",
          "audio_anchor_id": "audio-Great_Spotted_Woodpecker_1",
          "source_file": "20260712_054400.WAV",
          "offset_s": 4.629750566893424,
          "timestamp": "12 Jul 2026 05:44:04",
          "confidence": 0.9989627599716187,
          "verified": true
        },
        {
          "id": "Great_Spotted_Woodpecker_2",
          "spectrogram": "bird_report_20260714_175629_media/spectrograms/Great_Spotted_Woodpecker_2.png",
          "audio_report_file": "bird_report_20260714_175629.html",
          "audio_anchor_id": "audio-Great_Spotted_Woodpecker_2",
          "source_file": "20260711_192000.WAV",
          "offset_s": 55.82975056689342,
          "timestamp": "11 Jul 2026 19:20:55",
          "confidence": 0.6946529746055603,
          "verified": true
        }
      ]
    },
    {
      "common_name": "Carrion Crow",
      "latin_name": "Corvus corone",
      "best_confidence": 0.9986810088157654,
      "mean_confidence": 0.9985485076904297,
      "star_rating": 5,
      "is_marginal": false,
      "verification_reasons": [],
      "bng_categories": [],
      "bocc_status": "Green",
      "file_count": 2,
      "n_clips": 4,
      "first_detected": "2026-07-11T21:16:15.287710",
      "last_detected": "2026-07-12T06:00:44.475193",
      "peak_hour": 6,
      "hourly_counts": [
        0,
        0,
        0,
        0,
        0,
        0,
        2,
        0,
        0,
        0,
        0,
        0,
        0,
        0,
        0,
        0,
        0,
        0,
        0,
        0,
        0,
        2,
        0,
        0
      ],
      "clips": [
        {
          "id": "Carrion_Crow_1",
          "spectrogram": "bird_report_20260714_175629_media/spectrograms/Carrion_Crow_1.png",
          "audio_report_file": "bird_report_20260714_175629.html",
          "audio_anchor_id": "audio-Carrion_Crow_1",
          "source_file": "20260711_211600.WAV",
          "offset_s": 32.91165532879818,
          "timestamp": "11 Jul 2026 21:16:32",
          "confidence": 0.9986810088157654,
          "verified": true
        },
        {
          "id": "Carrion_Crow_2",
          "spectrogram": "bird_report_20260714_175629_media/spectrograms/Carrion_Crow_2.png",
          "audio_report_file": "bird_report_20260714_175629.html",
          "audio_anchor_id": "audio-Carrion_Crow_2",
          "source_file": "20260712_060000.WAV",
          "offset_s": 44.475192743764175,
          "timestamp": "12 Jul 2026 06:00:44",
          "confidence": 0.9986334443092346,
          "verified": true
        },
        {
          "id": "Carrion_Crow_3",
          "spectrogram": "bird_report_20260714_175629_media/spectrograms/Carrion_Crow_3.png",
          "audio_report_file": "bird_report_20260714_175629.html",
          "audio_anchor_id": "audio-Carrion_Crow_3",
          "source_file": "20260711_211600.WAV",
          "offset_s": 15.287709750566894,
          "timestamp": "11 Jul 2026 21:16:15",
          "confidence": 0.9984961748123169,
          "verified": true
        }
      ]
    },
    {
      "common_name": "European Robin",
      "latin_name": "Erithacus rubecula",
      "best_confidence": 0.9959580302238464,
      "mean_confidence": 0.9687255620956421,
      "star_rating": 5,
      "is_marginal": false,
      "verification_reasons": [],
      "bng_categories": [
        "understorey"
      ],
      "bocc_status": "Green",
      "file_count": 2,
      "n_clips": 11,
      "first_detected": "2026-07-12T04:36:13.731973",
      "last_detected": "2026-07-12T04:40:40.713560",
      "peak_hour": 4,
      "hourly_counts": [
        0,
        0,
        0,
        0,
        11,
        0,
        0,
        0,
        0,
        0,
        0,
        0,
        0,
        0,
        0,
        0,
        0,
        0,
        0,
        0,
        0,
        0,
        0,
        0
      ],
      "clips": [
        {
          "id": "European_Robin_1",
          "spectrogram": "bird_report_20260714_175629_media/spectrograms/European_Robin_1.png",
          "audio_report_file": "bird_report_20260714_175629.html",
          "audio_anchor_id": "audio-European_Robin_1",
          "source_file": "20260712_044000.WAV",
          "offset_s": 28.964263038548754,
          "timestamp": "12 Jul 2026 04:40:28",
          "confidence": 0.9959580302238464,
          "verified": true
        },
        {
          "id": "European_Robin_2",
          "spectrogram": "bird_report_20260714_175629_media/spectrograms/European_Robin_2.png",
          "audio_report_file": "bird_report_20260714_175629.html",
          "audio_anchor_id": "audio-European_Robin_2",
          "source_file": "20260712_044000.WAV",
          "offset_s": 17.19174603174603,
          "timestamp": "12 Jul 2026 04:40:17",
          "confidence": 0.9922714233398438,
          "verified": true
        },
        {
          "id": "European_Robin_3",
          "spectrogram": "bird_report_20260714_175629_media/spectrograms/European_Robin_3.png",
          "audio_report_file": "bird_report_20260714_175629.html",
          "audio_anchor_id": "audio-European_Robin_3",
          "source_file": "20260712_044000.WAV",
          "offset_s": 7.996643990929705,
          "timestamp": "12 Jul 2026 04:40:07",
          "confidence": 0.9899932742118835,
          "verified": true
        }
      ]
    },
    {
      "common_name": "Eurasian Treecreeper",
      "latin_name": "Certhia familiaris",
      "best_confidence": 0.9938936829566956,
      "mean_confidence": 0.8417638540267944,
      "star_rating": 4,
      "is_marginal": false,
      "verification_reasons": [],
      "bng_categories": [
        "deadwood"
      ],
      "bocc_status": "Green",
      "file_count": 3,
      "n_clips": 9,
      "first_detected": "2026-07-12T06:32:46.727528",
      "last_detected": "2026-07-12T09:48:56.363810",
      "peak_hour": 6,
      "hourly_counts": [
        0,
        0,
        0,
        0,
        0,
        0,
        4,
        0,
        3,
        2,
        0,
        0,
        0,
        0,
        0,
        0,
        0,
        0,
        0,
        0,
        0,
        0,
        0,
        0
      ],
      "clips": [
        {
          "id": "Eurasian_Treecreeper_1",
          "spectrogram": "bird_report_20260714_175629_media/spectrograms/Eurasian_Treecreeper_1.png",
          "audio_report_file": "bird_report_20260714_175629.html",
          "audio_anchor_id": "audio-Eurasian_Treecreeper_1",
          "source_file": "20260712_094800.WAV",
          "offset_s": 54.041814058956916,
          "timestamp": "12 Jul 2026 09:48:54",
          "confidence": 0.9938936829566956,
          "verified": true
        },
        {
          "id": "Eurasian_Treecreeper_2",
          "spectrogram": "bird_report_20260714_175629_media/spectrograms/Eurasian_Treecreeper_2.png",
          "audio_report_file": "bird_report_20260714_175629.html",
          "audio_anchor_id": "audio-Eurasian_Treecreeper_2",
          "source_file": "20260712_094800.WAV",
          "offset_s": 56.36380952380952,
          "timestamp": "12 Jul 2026 09:48:56",
          "confidence": 0.992708683013916,
          "verified": true
        },
        {
          "id": "Eurasian_Treecreeper_3",
          "spectrogram": "bird_report_20260714_175629_media/spectrograms/Eurasian_Treecreeper_3.png",
          "audio_report_file": "bird_report_20260714_175629.html",
          "audio_anchor_id": "audio-Eurasian_Treecreeper_3",
          "source_file": "20260712_063200.WAV",
          "offset_s": 52.83437641723356,
          "timestamp": "12 Jul 2026 06:32:52",
          "confidence": 0.9822738766670227,
          "verified": true
        }
      ]
    },
    {
      "common_name": "Common Wood Pigeon",
      "latin_name": "Columba palumbus",
      "best_confidence": 0.9981990456581116,
      "mean_confidence": 0.9978634715080261,
      "star_rating": 5,
      "is_marginal": true,
      "verification_reasons": [
        "Detected in only one recording file \u2014 limited survey presence"
      ],
      "bng_categories": [
        "canopy"
      ],
      "bocc_status": "Green",
      "file_count": 1,
      "n_clips": 5,
      "first_detected": "2026-07-11T21:12:43.917914",
      "last_detected": "2026-07-11T21:12:53.623855",
      "peak_hour": 21,
      "hourly_counts": [
        0,
        0,
        0,
        0,
        0,
        0,
        0,
        0,
        0,
        0,
        0,
        0,
        0,
        0,
        0,
        0,
        0,
        0,
        0,
        0,
        0,
        5,
        0,
        0
      ],
      "clips": [
        {
          "id": "Common_Wood_Pigeon_1",
          "spectrogram": "bird_report_20260714_175629_media/spectrograms/Common_Wood_Pigeon_1.png",
          "audio_report_file": "bird_report_20260714_175629.html",
          "audio_anchor_id": "audio-Common_Wood_Pigeon_1",
          "source_file": "20260711_211200.WAV",
          "offset_s": 50.907120181405894,
          "timestamp": "11 Jul 2026 21:12:50",
          "confidence": 0.9981990456581116,
          "verified": false
        },
        {
          "id": "Common_Wood_Pigeon_2",
          "spectrogram": "bird_report_20260714_175629_media/spectrograms/Common_Wood_Pigeon_2.png",
          "audio_report_file": "bird_report_20260714_175629.html",
          "audio_anchor_id": "audio-Common_Wood_Pigeon_2",
          "source_file": "20260711_211200.WAV",
          "offset_s": 53.62385487528345,
          "timestamp": "11 Jul 2026 21:12:53",
          "confidence": 0.9980649352073669,
          "verified": false
        },
        {
          "id": "Common_Wood_Pigeon_3",
          "spectrogram": "bird_report_20260714_175629_media/spectrograms/Common_Wood_Pigeon_3.png",
          "audio_report_file": "bird_report_20260714_175629.html",
          "audio_anchor_id": "audio-Common_Wood_Pigeon_3",
          "source_file": "20260711_211200.WAV",
          "offset_s": 48.58512471655329,
          "timestamp": "11 Jul 2026 21:12:48",
          "confidence": 0.9979817867279053,
          "verified": false
        }
      ]
    },
    {
      "common_name": "Coal Tit",
      "latin_name": "Periparus ater",
      "best_confidence": 0.982353687286377,
      "mean_confidence": 0.4587700068950653,
      "star_rating": 4,
      "is_marginal": true,
      "verification_reasons": [
        "Detected in only one recording file \u2014 limited survey presence"
      ],
      "bng_categories": [
        "canopy"
      ],
      "bocc_status": "Green",
      "file_count": 1,
      "n_clips": 6,
      "first_detected": "2026-07-12T09:24:33.352834",
      "last_detected": "2026-07-12T09:24:56.247710",
      "peak_hour": 9,
      "hourly_counts": [
        0,
        0,
        0,
        0,
        0,
        0,
        0,
        0,
        0,
        6,
        0,
        0,
        0,
        0,
        0,
        0,
        0,
        0,
        0,
        0,
        0,
        0,
        0,
        0
      ],
      "clips": [
        {
          "id": "Coal_Tit_1",
          "spectrogram": "bird_report_20260714_175629_media/spectrograms/Coal_Tit_1.png",
          "audio_report_file": "bird_report_20260714_175629.html",
          "audio_anchor_id": "audio-Coal_Tit_1",
          "source_file": "20260712_092400.WAV",
          "offset_s": 33.35283446712018,
          "timestamp": "12 Jul 2026 09:24:33",
          "confidence": 0.982353687286377,
          "verified": false
        },
        {
          "id": "Coal_Tit_2",
          "spectrogram": "bird_report_20260714_175629_media/spectrograms/Coal_Tit_2.png",
          "audio_report_file": "bird_report_20260714_175629.html",
          "audio_anchor_id": "audio-Coal_Tit_2",
          "source_file": "20260712_092400.WAV",
          "offset_s": 56.24770975056689,
          "timestamp": "12 Jul 2026 09:24:56",
          "confidence": 0.4363243579864502,
          "verified": false
        },
        {
          "id": "Coal_Tit_3",
          "spectrogram": "bird_report_20260714_175629_media/spectrograms/Coal_Tit_3.png",
          "audio_report_file": "bird_report_20260714_175629.html",
          "audio_anchor_id": "audio-Coal_Tit_3",
          "source_file": "20260712_092400.WAV",
          "offset_s": 46.42566893424036,
          "timestamp": "12 Jul 2026 09:24:46",
          "confidence": 0.4216012954711914,
          "verified": false
        }
      ]
    },
    {
      "common_name": "European Green Woodpecker",
      "latin_name": "Picus viridis",
      "best_confidence": 0.9677268862724304,
      "mean_confidence": 0.9677268862724304,
      "star_rating": 5,
      "is_marginal": true,
      "verification_reasons": [
        "Detected in only one recording file \u2014 limited survey presence"
      ],
      "bng_categories": [
        "canopy",
        "deadwood"
      ],
      "bocc_status": "Green",
      "file_count": 1,
      "n_clips": 1,
      "first_detected": "2026-07-12T06:00:53.902494",
      "last_detected": "2026-07-12T06:00:53.902494",
      "peak_hour": 6,
      "hourly_counts": [
        0,
        0,
        0,
        0,
        0,
        0,
        1,
        0,
        0,
        0,
        0,
        0,
        0,
        0,
        0,
        0,
        0,
        0,
        0,
        0,
        0,
        0,
        0,
        0
      ],
      "clips": [
        {
          "id": "European_Green_Woodpecker_1",
          "spectrogram": "bird_report_20260714_175629_media/spectrograms/European_Green_Woodpecker_1.png",
          "audio_report_file": "bird_report_20260714_175629.html",
          "audio_anchor_id": "audio-European_Green_Woodpecker_1",
          "source_file": "20260712_060000.WAV",
          "offset_s": 53.90249433106576,
          "timestamp": "12 Jul 2026 06:00:53",
          "confidence": 0.9677268862724304,
          "verified": false
        }
      ]
    },
    {
      "common_name": "Blue Tit",
      "latin_name": "Cyanistes caeruleus",
      "best_confidence": 0.9538038969039917,
      "mean_confidence": 0.8909374475479126,
      "star_rating": 3,
      "is_marginal": true,
      "verification_reasons": [
        "Detected in only one recording file \u2014 limited survey presence"
      ],
      "bng_categories": [],
      "bocc_status": "Green",
      "file_count": 1,
      "n_clips": 2,
      "first_detected": "2026-07-12T09:24:05.976508",
      "last_detected": "2026-07-12T09:24:53.229116",
      "peak_hour": 9,
      "hourly_counts": [
        0,
        0,
        0,
        0,
        0,
        0,
        0,
        0,
        0,
        2,
        0,
        0,
        0,
        0,
        0,
        0,
        0,
        0,
        0,
        0,
        0,
        0,
        0,
        0
      ],
      "clips": [
        {
          "id": "Blue_Tit_1",
          "spectrogram": "bird_report_20260714_175629_media/spectrograms/Blue_Tit_1.png",
          "audio_report_file": "bird_report_20260714_175629.html",
          "audio_anchor_id": "audio-Blue_Tit_1",
          "source_file": "20260712_092400.WAV",
          "offset_s": 53.229115646258506,
          "timestamp": "12 Jul 2026 09:24:53",
          "confidence": 0.9538038969039917,
          "verified": false
        },
        {
          "id": "Blue_Tit_2",
          "spectrogram": "bird_report_20260714_175629_media/spectrograms/Blue_Tit_2.png",
          "audio_report_file": "bird_report_20260714_175629.html",
          "audio_anchor_id": "audio-Blue_Tit_2",
          "source_file": "20260712_092400.WAV",
          "offset_s": 5.976507936507937,
          "timestamp": "12 Jul 2026 09:24:05",
          "confidence": 0.8280710577964783,
          "verified": false
        }
      ]
    },
    {
      "common_name": "Dunnock",
      "latin_name": "Prunella modularis",
      "best_confidence": 0.4578263759613037,
      "mean_confidence": 0.40874338150024414,
      "star_rating": 1,
      "is_marginal": true,
      "verification_reasons": [
        "Low AI confidence (1\u2605 \u2014 below 3\u2605 threshold)",
        "Detected in only one recording file \u2014 limited survey presence"
      ],
      "bng_categories": [
        "ground"
      ],
      "bocc_status": "Amber",
      "file_count": 1,
      "n_clips": 2,
      "first_detected": "2026-07-12T05:00:27.989025",
      "last_detected": "2026-07-12T05:00:41.990658",
      "peak_hour": 5,
      "hourly_counts": [
        0,
        0,
        0,
        0,
        0,
        2,
        0,
        0,
        0,
        0,
        0,
        0,
        0,
        0,
        0,
        0,
        0,
        0,
        0,
        0,
        0,
        0,
        0,
        0
      ],
      "clips": [
        {
          "id": "Dunnock_1",
          "spectrogram": "bird_report_20260714_175629_media/spectrograms/Dunnock_1.png",
          "audio_report_file": "bird_report_20260714_175629.html",
          "audio_anchor_id": "audio-Dunnock_1",
          "source_file": "20260712_050000.WAV",
          "offset_s": 27.989024943310657,
          "timestamp": "12 Jul 2026 05:00:27",
          "confidence": 0.4578263759613037,
          "verified": false
        },
        {
          "id": "Dunnock_2",
          "spectrogram": "bird_report_20260714_175629_media/spectrograms/Dunnock_2.png",
          "audio_report_file": "bird_report_20260714_175629.html",
          "audio_anchor_id": "audio-Dunnock_2",
          "source_file": "20260712_050000.WAV",
          "offset_s": 41.99065759637188,
          "timestamp": "12 Jul 2026 05:00:41",
          "confidence": 0.35966038703918457,
          "verified": false
        }
      ]
    },
    {
      "common_name": "Jay",
      "latin_name": "Garrulus glandarius",
      "best_confidence": 0.42130953073501587,
      "mean_confidence": 0.42130953073501587,
      "star_rating": 1,
      "is_marginal": true,
      "verification_reasons": [
        "Low AI confidence (1\u2605 \u2014 below 3\u2605 threshold)",
        "Detected in only one recording file \u2014 limited survey presence"
      ],
      "bng_categories": [
        "canopy"
      ],
      "bocc_status": "Green",
      "file_count": 1,
      "n_clips": 1,
      "first_detected": "2026-07-11T21:04:57.757007",
      "last_detected": "2026-07-11T21:04:57.757007",
      "peak_hour": 21,
      "hourly_counts": [
        0,
        0,
        0,
        0,
        0,
        0,
        0,
        0,
        0,
        0,
        0,
        0,
        0,
        0,
        0,
        0,
        0,
        0,
        0,
        0,
        0,
        1,
        0,
        0
      ],
      "clips": [
        {
          "id": "Jay_1",
          "spectrogram": "bird_report_20260714_175629_media/spectrograms/Jay_1.png",
          "audio_report_file": "bird_report_20260714_175629.html",
          "audio_anchor_id": "audio-Jay_1",
          "source_file": "20260711_210400.WAV",
          "offset_s": 57.75700680272109,
          "timestamp": "11 Jul 2026 21:04:57",
          "confidence": 0.42130953073501587,
          "verified": false
        }
      ]
    }
  ],
  "report_html_file": "bird_report_20260714_175629.html"
}